drillcore_transformations_py/Transform_scripts.py
drillcore_transformations_py/Transform_workflow.py
drillcore_transformations_py/__init__.py
drillcore_transformations_py/cli.py
drillcore_transformations_py/drillcore_transformations_dev.py
drillcore_transformations_py/gamma_rotation.py
drillcore_transformations_py/rotation_dev.py
drillcore_transformations_py/transformations.py
drillcore_transformations_py/usage.py
drillcore_transformations_py/visualizations.py
drillcore_transformations_py-0.1.0.dist-info/AUTHORS.rst
drillcore_transformations_py-0.1.0.dist-info/LICENSE
drillcore_transformations_py-0.1.0.dist-info/METADATA
drillcore_transformations_py-0.1.0.dist-info/WHEEL
drillcore_transformations_py-0.1.0.dist-info/entry_points.txt
drillcore_transformations_py-0.1.0.dist-info/top_level.txt
drillcore_transformations_py-0.1.0.dist-info/RECORD
