Metadata-Version: 2.1
Name: drillcore-transformations-py
Version: 0.1.0
Summary: Drillcore Transformations allows for alpha, beta and gamma drillcore transformations.
Home-page: https://github.com/nialov/drillcore-transformations
Author: Nikolas Ovaskainen
Author-email: nikolasovaskainen@gmail.com
License: GNU General Public License v3
Keywords: drillcore_transformations_py
Platform: UNKNOWN
Classifier: Development Status :: 2 - Pre-Alpha
Classifier: Intended Audience :: Developers
Classifier: License :: OSI Approved :: GNU General Public License v3 (GPLv3)
Classifier: Natural Language :: English
Classifier: Programming Language :: Python :: 3.8
Requires-Python: >=3.6
Requires-Dist: pip
Requires-Dist: Click
Requires-Dist: numpy
Requires-Dist: pandas
Requires-Dist: matplotlib
Requires-Dist: sympy
Requires-Dist: xlrd
Requires-Dist: openpyxl
